mcp_http_streamable/__init__.py
mcp_http_streamable/server.py
mcp_http_streamable_ysx_test-0.1.1.dist-info/METADATA
mcp_http_streamable_ysx_test-0.1.1.dist-info/WHEEL
mcp_http_streamable_ysx_test-0.1.1.dist-info/entry_points.txt
mcp_http_streamable_ysx_test-0.1.1.dist-info/top_level.txt
mcp_http_streamable_ysx_test-0.1.1.dist-info/RECORD
