Metadata-Version: 2.4
Name: mcp-http-streamable-ysx-test
Version: 0.1.1
Summary: 输入OpenWeather-API-KEY，获取天气信息。
Requires-Python: >=3.10
Requires-Dist: httpx>=0.28.1
Requires-Dist: mcp>=1.8.0
